pbzlib/__init__.py
pbzlib/constants.py
pbzlib/reader.py
pbzlib/writer.py
pbzlib-0.20211124.dist-info/LICENSE
pbzlib-0.20211124.dist-info/METADATA
pbzlib-0.20211124.dist-info/WHEEL
pbzlib-0.20211124.dist-info/top_level.txt
pbzlib-0.20211124.dist-info/RECORD
