Metadata-Version: 2.1
Name: pbzlib
Version: 0.20211124
Summary: Library for serializing a list of protobuf objects
Home-page: https://github.com/fabgeyer/pbzlib-py
Author: fabgeyer
License: MIT
Keywords: protobuf
Platform: UNKNOWN
Classifier: Development Status :: 3 - Alpha
Classifier: Environment :: Console
Classifier: Intended Audience :: Science/Research
Classifier: License :: OSI Approved :: BSD License
License-File: LICENSE
Requires-Dist: protobuf
